django_gunicorn_audit_logs/__init__.py
django_gunicorn_audit_logs/admin.py
django_gunicorn_audit_logs/apps.py
django_gunicorn_audit_logs/choices.py
django_gunicorn_audit_logs/email_utils.py
django_gunicorn_audit_logs/gunicorn_config.py
django_gunicorn_audit_logs/middleware.py
django_gunicorn_audit_logs/models.py
django_gunicorn_audit_logs/mongo_storage.py
django_gunicorn_audit_logs/routers.py
django_gunicorn_audit_logs/tasks.py
django_gunicorn_audit_logs/utils.py
django_gunicorn_audit_logs/management/__init__.py
django_gunicorn_audit_logs/management/commands/__init__.py
django_gunicorn_audit_logs/management/commands/cleanup_audit_logs.py
django_gunicorn_audit_logs/migrations/0001_initial.py
django_gunicorn_audit_logs/migrations/0002_gunicornlogmodel.py
django_gunicorn_audit_logs/migrations/0003_update_gunicornlogmodel_method_field.py
django_gunicorn_audit_logs/migrations/__init__.py
django_gunicorn_audit_logs-0.3.5.dist-info/licenses/LICENSE
tests/__init__.py
tests/settings.py
tests/test_commands.py
tests/test_middleware.py
tests/test_utils.py
tests/urls.py
tests/views.py
django_gunicorn_audit_logs-0.3.5.dist-info/METADATA
django_gunicorn_audit_logs-0.3.5.dist-info/WHEEL
django_gunicorn_audit_logs-0.3.5.dist-info/top_level.txt
django_gunicorn_audit_logs-0.3.5.dist-info/RECORD
