Metadata-Version: 2.4
Name: django-gunicorn-audit-logs
Version: 0.3.5
Summary: A Django middleware for logging requests and responses to PostgreSQL with dual logging capabilities
Home-page: https://github.com/paymeinfra/hueytech_audit_logs
Author: payme-alok
Author-email: infra@paymeindia.in
Classifier: Development Status :: 4 - Beta
Classifier: Framework :: Django
Classifier: Intended Audience :: Developers
Classifier: License :: OSI Approved :: MIT License
Classifier: Programming Language :: Python :: 3
Classifier: Programming Language :: Python :: 3.8
Classifier: Programming Language :: Python :: 3.9
Classifier: Programming Language :: Python :: 3.10
Requires-Python: >=3.8
License-File: LICENSE
Requires-Dist: Django>=3.2
Requires-Dist: psycopg2-binary>=2.9.3
Requires-Dist: gunicorn>=20.1.0
Requires-Dist: boto3>=1.26.0
Requires-Dist: python-dotenv>=0.21.0
Provides-Extra: async
Requires-Dist: celery>=5.2.0; extra == "async"
Provides-Extra: mongo
Requires-Dist: pymongo>=4.0.0; extra == "mongo"
Requires-Dist: dnspython>=2.0.0; extra == "mongo"
Dynamic: author
Dynamic: author-email
Dynamic: classifier
Dynamic: description
Dynamic: description-content-type
Dynamic: home-page
Dynamic: license-file
Dynamic: provides-extra
Dynamic: requires-dist
Dynamic: requires-python
Dynamic: summary
